Metadata-Version: 1.1
Name: python-cern-sso
Version: 1.3.3
Summary: Cern Single-Single-Sign-On driver
Home-page: https://gitlab.cern.ch/astjerna/cern-sso-python
Author: Albin Stjerna
Author-email: albin.stjerna@cern.ch
License: MIT
Keywords: authentication sso cern
Platform: UNKNOWN
Classifier: Development Status :: 3 - Alpha
Classifier: Intended Audience :: Developers
Classifier: License :: OSI Approved :: MIT License
Classifier: Programming Language :: Python :: 2.6
Classifier: Programming Language :: Python :: 2.7
Classifier: Programming Language :: Python :: 3
